{
  "input": {
    "type": "sop",
    "steps": "1. Clean equipment\n2. Prepare sanitizing solution\n3. Apply solution to surfaces\n4. Allow contact time\n5. Rinse thoroughly\n6. Verify cleanliness\n7. Document procedure",
    "roles": "Document Control Specialist, Department Manager, Quality Assurance Reviewer",
    "notes": "Maintain controlled environment conditions as specified in ENV-SOP-002."
  },
  "generated_content": "\n# STANDARD OPERATING PROCEDURE\n## Quality Control Process\n\n**Document ID:** SOP-801-43  \n**Version:** 1.0  \n**Effective Date:** 2025-09-11  \n**Review Date:** 2026-10-09  \n\n### 1. PURPOSE\nThis Standard Operating Procedure (SOP) defines the process for quality control process in a consistent and compliant manner.\n\n### 2. SCOPE\nThis procedure applies to all personnel involved in quality control process.\n\n### 3. RESPONSIBILITIES\n**Document Control Specialist**\n\n**Department Manager**\n- Oversee execution of the procedure\n- Review completed documentation\n- Address deviations and issues\n\n**Quality Assurance Reviewer**\n- Review and approve documentation\n- Ensure compliance with regulations\n- Perform quality checks as specified\n\n\n\n### 4. MATERIALS AND EQUIPMENT\n- Heating plate\n- Autoclave\n- Incubator\n- Moisture analyzer\n- Centrifuge\n\n### 5. PROCEDURE\n1. Clean equipment\n\n2. Prepare sanitizing solution\n\n3. Apply solution to surfaces\n\n4. Allow contact time\n\n5. Rinse thoroughly\n\n6. Verify cleanliness\n\n7. Document procedure\n\n### 6. DOCUMENTATION\nThe following records must be maintained:\n- Test results\n- Training records\n- Change control documentation\n\n### 7. REFERENCES\n- ISO 9001:2015 Quality Management Systems\n- Equipment Manual: Model XYZ-123\n- USP <1116> Microbiological Control and Monitoring\n\n### 8. REVISION HISTORY\n| Version | Date | Description of Changes | Author | Approved By |\n|---------|------|------------------------|--------|-------------|\n| 1.0 | 2025-09-11 | Initial release | | |\n\n### 9. APPROVALS\n| Role | Name | Signature | Date |\n|------|------|-----------|------|\n| Author | | | |\n| Reviewer | | | |\n| Approver | | | |\n    ",
  "doc_type": "sop",
  "metadata": {
    "model_version": "v1",
    "template_type": "standard",
    "timestamp": "2025-07-19T12:00:00"
  },
  "feedback": {
    "score": 4.969401188504509,
    "text": "Generated from industry standard templates"
  }
}